configurun/__init__.py
configurun/app/__init__.py
configurun/app/create_run.py
configurun/app/main_window.py
configurun/app/network_main_window.py
configurun/app/models/__init__.py
configurun/app/models/run_queue_console_model.py
configurun/app/models/run_queue_table_model.py
configurun/app/ui/__init__.py
configurun/app/ui/main_window_ui.py
configurun/app/ui/network_login_widget_ui.py
configurun/app/ui/run_queue_widget_ui.py
configurun/app/views/__init__.py
configurun/app/views/run_queue_tree_view.py
configurun/app/widgets/__init__.py
configurun/app/widgets/network_login_widget.py
configurun/app/widgets/run_queue_widget.py
configurun/classes/__init__.py
configurun/classes/method_call_interceptor.py
configurun/classes/run_queue.py
configurun/classes/run_queue_client.py
configurun/classes/run_queue_datatypes.py
configurun/classes/run_queue_server.py
configurun/configuration/__init__.py
configurun/configuration/argparse_to_dataclass.py
configurun/configuration/base_options.py
configurun/configuration/configuration.py
configurun/configuration/configuration_model.py
configurun/examples/__init__.py
configurun/examples/example_argparse.py
configurun/examples/example_configuration.py
configurun/examples/example_configuration_sklearn.py
configurun/examples/example_target_function.py
configurun/examples/example_options/__init__.py
configurun/examples/example_options/example_options.py
configurun/examples/example_options/example_sklearn_options.py
configurun/res/__init__.py
configurun/res/app_resources_rc.py
configurun/server/__init__.py
configurun/server/create_server.py
configurun-0.2.5.dist-info/LICENSE
configurun-0.2.5.dist-info/METADATA
configurun-0.2.5.dist-info/WHEEL
configurun-0.2.5.dist-info/top_level.txt
configurun-0.2.5.dist-info/RECORD
