Metadata-Version: 2.1
Name: configurun
Version: 0.2.5
Summary: Cross-platform user-interface tools to create and manage (machine learning) configurations and run them automatically and remotely.
Home-page: https://github.com/Woutah/configurun
Author: Wouter Stokman
License: LGPLv2
License-File: LICENSE
Requires-Dist: PySide6 >=6.0.0
Requires-Dist: pathos >=0.3.0
Requires-Dist: setuptools >=65.0.0
Requires-Dist: dill >=0.3.0
Requires-Dist: multiprocess >=0.70.00
Requires-Dist: numpydoc >=1.4.0
Requires-Dist: pycryptodome >=3.10.0
Requires-Dist: pyside6-utils <1.3.0,>=1.2.1
Requires-Dist: PySignal >=1.1.1
